{
    "size":0.45,
    "maxLife":20,
    "type":"std",
    "price":200,
    "ability":{
        "type":"teleport",
        "angle":120,
        "rechargeTime":4
    },
    "gunSlots":[
        {
            "position":"0.673076923 0.494117647",
            "isUnderneathHull":false,
            "allowsRotation":true
        }
    ],
    "engine":"core:imperialEngine",
    "e1Pos":"0.019230769 0.458823529",
    "e2Pos":"0.019230769 0.535294118",
    "lightSrcPoss":[

    ],
    "rigidBody":{
        "name":"formicSmall",
        "imagePath":"formicSmall.png",
        "origin":{
            "x":0.4912499785423279,
            "y":0.5087499618530273
        },
        "polygons":[
            [
                {
                    "x":0.06538461893796921,
                    "y":0.5884615182876587
                },
                {
                    "x":0.023076923564076424,
                    "y":0.5807692408561707
                },
                {
                    "x":0.05384615436196327,
                    "y":0.5653846263885498
                },
                {
                    "x":0.12591595947742462,
                    "y":0.5806721448898315
                }
            ],
            [
                {
                    "x":0.12591595947742462,
                    "y":0.5806721448898315
                },
                {
                    "x":0.11923076957464218,
                    "y":0.5923076868057251
                },
                {
                    "x":0,
                    "y":0.642307698726654
                },
                {
                    "x":0.06538461893796921,
                    "y":0.5884615182876587
                }
            ],
            [
                {
                    "x":0.18076923489570618,
                    "y":0.5923076868057251
                },
                {
                    "x":0.13076923787593842,
                    "y":0.615384578704834
                },
                {
                    "x":0.11923076957464218,
                    "y":0.5923076868057251
                },
                {
                    "x":0.12591595947742462,
                    "y":0.5806721448898315
                }
            ],
            [
                {
                    "x":0.05000000074505806,
                    "y":0.45769232511520386
                },
                {
                    "x":0.057692307978868484,
                    "y":0.442307710647583
                },
                {
                    "x":0.05384615436196327,
                    "y":0.5461538434028625
                },
                {
                    "x":0.01923076994717121,
                    "y":0.5346153974533081
                }
            ],
            [
                {
                    "x":0.01923076994717121,
                    "y":0.5346153974533081
                },
                {
                    "x":0.01923076994717121,
                    "y":0.45769232511520386
                },
                {
                    "x":0.05000000074505806,
                    "y":0.45769232511520386
                }
            ],
            [
                {
                    "x":0.057692307978868484,
                    "y":0.41538459062576294
                },
                {
                    "x":0.0615384615957737,
                    "y":0.3999999761581421
                },
                {
                    "x":0.057692307978868484,
                    "y":0.442307710647583
                }
            ],
            [
                {
                    "x":0.057692307978868484,
                    "y":0.442307710647583
                },
                {
                    "x":0.03076923079788685,
                    "y":0.41538459062576294
                },
                {
                    "x":0.057692307978868484,
                    "y":0.41538459062576294
                }
            ],
            [
                {
                    "x":0.0615384615957737,
                    "y":0.3999999761581421
                },
                {
                    "x":0.003846153849735856,
                    "y":0.36153846979141235
                },
                {
                    "x":0.13076923787593842,
                    "y":0.4115384817123413
                }
            ],
            [
                {
                    "x":0.23846153914928436,
                    "y":0.4115384817123413
                },
                {
                    "x":0.33076924085617065,
                    "y":0.38846153020858765
                },
                {
                    "x":0.3192307651042938,
                    "y":0.6038461923599243
                },
                {
                    "x":0.18076923489570618,
                    "y":0.5923076868057251
                }
            ],
            [
                {
                    "x":0.18076923489570618,
                    "y":0.5923076868057251
                },
                {
                    "x":0.17307692766189575,
                    "y":0.4076923131942749
                },
                {
                    "x":0.23846153914928436,
                    "y":0.4115384817123413
                }
            ],
            [
                {
                    "x":0.18076923489570618,
                    "y":0.5923076868057251
                },
                {
                    "x":0.13076923787593842,
                    "y":0.4115384817123413
                },
                {
                    "x":0.13076923787593842,
                    "y":0.39230769872665405
                },
                {
                    "x":0.17307692766189575,
                    "y":0.4076923131942749
                }
            ],
            [
                {
                    "x":0.18076923489570618,
                    "y":0.5923076868057251
                },
                {
                    "x":0.05384615436196327,
                    "y":0.5653846263885498
                },
                {
                    "x":0.05384615436196327,
                    "y":0.5461538434028625
                },
                {
                    "x":0.057692307978868484,
                    "y":0.442307710647583
                },
                {
                    "x":0.0615384615957737,
                    "y":0.3999999761581421
                },
                {
                    "x":0.13076923787593842,
                    "y":0.4115384817123413
                }
            ],
            [
                {
                    "x":0.75,
                    "y":0.2576923370361328
                },
                {
                    "x":0.6807692050933838,
                    "y":0.27307695150375366
                },
                {
                    "x":0.3153846263885498,
                    "y":0.2192307710647583
                },
                {
                    "x":0.26153847575187683,
                    "y":0.20769232511520386
                },
                {
                    "x":0.29615384340286255,
                    "y":0.192307710647583
                },
                {
                    "x":0.6384615302085876,
                    "y":0.1846153736114502
                },
                {
                    "x":0.8346154093742371,
                    "y":0.19999998807907104
                }
            ],
            [
                {
                    "x":0.8346154093742371,
                    "y":0.19999998807907104
                },
                {
                    "x":0.9692307710647583,
                    "y":0.23461538553237915
                },
                {
                    "x":0.9961538314819336,
                    "y":0.2538461685180664
                },
                {
                    "x":0.75,
                    "y":0.2576923370361328
                }
            ],
            [
                {
                    "x":0.6538461446762085,
                    "y":0.307692289352417
                },
                {
                    "x":0.6692307591438293,
                    "y":0.3153846263885498
                },
                {
                    "x":0.6153846383094788,
                    "y":0.3192307949066162
                },
                {
                    "x":0.6321182250976562,
                    "y":0.30919069051742554
                }
            ],
            [
                {
                    "x":0.6538461446762085,
                    "y":0.29615384340286255
                },
                {
                    "x":0.6692307591438293,
                    "y":0.30384618043899536
                },
                {
                    "x":0.6538461446762085,
                    "y":0.307692289352417
                },
                {
                    "x":0.6321182250976562,
                    "y":0.30919069051742554
                }
            ],
            [
                {
                    "x":0.607692301273346,
                    "y":0.35384613275527954
                },
                {
                    "x":0.6230769157409668,
                    "y":0.36153846979141235
                },
                {
                    "x":0.5807692408561707,
                    "y":0.36538463830947876
                },
                {
                    "x":0.522567629814148,
                    "y":0.33469653129577637
                }
            ],
            [
                {
                    "x":0.522567629814148,
                    "y":0.33469653129577637
                },
                {
                    "x":0.5961538553237915,
                    "y":0.3423076868057251
                },
                {
                    "x":0.6230769157409668,
                    "y":0.3500000238418579
                },
                {
                    "x":0.607692301273346,
                    "y":0.35384613275527954
                }
            ],
            [
                {
                    "x":0.3692307770252228,
                    "y":0.2538461685180664
                },
                {
                    "x":0.6153846383094788,
                    "y":0.3192307949066162
                },
                {
                    "x":0.5961538553237915,
                    "y":0.3423076868057251
                },
                {
                    "x":0.522567629814148,
                    "y":0.33469653129577637
                }
            ],
            [
                {
                    "x":0.3692307770252228,
                    "y":0.2538461685180664
                },
                {
                    "x":0.3153846263885498,
                    "y":0.2192307710647583
                },
                {
                    "x":0.6807692050933838,
                    "y":0.27307695150375366
                },
                {
                    "x":0.6538461446762085,
                    "y":0.29615384340286255
                },
                {
                    "x":0.6153846383094788,
                    "y":0.3192307949066162
                }
            ],
            [
                {
                    "x":0.5807692408561707,
                    "y":0.36538463830947876
                },
                {
                    "x":0.5730769038200378,
                    "y":0.38461536169052124
                },
                {
                    "x":0.36153846979141235,
                    "y":0.3115384578704834
                },
                {
                    "x":0.3153846263885498,
                    "y":0.2846153974533081
                },
                {
                    "x":0.32307693362236023,
                    "y":0.26153844594955444
                },
                {
                    "x":0.3692307770252228,
                    "y":0.2538461685180664
                }
            ],
            [
                {
                    "x":0.5730769038200378,
                    "y":0.38461536169052124
                },
                {
                    "x":0.6038461327552795,
                    "y":0.39230769872665405
                },
                {
                    "x":0.5884615182876587,
                    "y":0.39615386724472046
                }
            ],
            [
                {
                    "x":0.5884615182876587,
                    "y":0.39615386724472046
                },
                {
                    "x":0.6038461327552795,
                    "y":0.4038461446762085
                },
                {
                    "x":0.5846154093742371,
                    "y":0.4038461446762085
                }
            ],
            [
                {
                    "x":0.6692307591438293,
                    "y":0.4692307710647583
                },
                {
                    "x":0.7153846025466919,
                    "y":0.4961538314819336
                },
                {
                    "x":0.7038461565971375,
                    "y":0.5230768918991089
                },
                {
                    "x":0.6653845906257629,
                    "y":0.5384615659713745
                }
            ],
            [
                {
                    "x":0.6653845906257629,
                    "y":0.5384615659713745
                },
                {
                    "x":0.607692301273346,
                    "y":0.4307692050933838
                },
                {
                    "x":0.6692307591438293,
                    "y":0.44615381956100464
                },
                {
                    "x":0.6692307591438293,
                    "y":0.4692307710647583
                }
            ],
            [
                {
                    "x":0.5884615182876587,
                    "y":0.607692301273346
                },
                {
                    "x":0.6038461327552795,
                    "y":0.615384578704834
                },
                {
                    "x":0.5769230723381042,
                    "y":0.6192307472229004
                },
                {
                    "x":0.5817307829856873,
                    "y":0.6072115302085876
                }
            ],
            [
                {
                    "x":0.5846154093742371,
                    "y":0.6000000238418579
                },
                {
                    "x":0.6038461327552795,
                    "y":0.6038461923599243
                },
                {
                    "x":0.5884615182876587,
                    "y":0.607692301273346
                },
                {
                    "x":0.5817307829856873,
                    "y":0.6072115302085876
                }
            ],
            [
                {
                    "x":0.5769230723381042,
                    "y":0.6192307472229004
                },
                {
                    "x":0.36153846979141235,
                    "y":0.6846153736114502
                },
                {
                    "x":0.33076924085617065,
                    "y":0.6499999761581421
                },
                {
                    "x":0.3192307651042938,
                    "y":0.6038461923599243
                },
                {
                    "x":0.33076924085617065,
                    "y":0.38846153020858765
                },
                {
                    "x":0.3346153795719147,
                    "y":0.3461538553237915
                }
            ],
            [
                {
                    "x":0.3346153795719147,
                    "y":0.3461538553237915
                },
                {
                    "x":0.36153846979141235,
                    "y":0.3115384578704834
                },
                {
                    "x":0.5846154093742371,
                    "y":0.4038461446762085
                },
                {
                    "x":0.607692301273346,
                    "y":0.4307692050933838
                },
                {
                    "x":0.5884615182876587,
                    "y":0.5846153497695923
                },
                {
                    "x":0.5846154093742371,
                    "y":0.6000000238418579
                },
                {
                    "x":0.5769230723381042,
                    "y":0.6192307472229004
                }
            ],
            [
                {
                    "x":0.607692301273346,
                    "y":0.4307692050933838
                },
                {
                    "x":0.6653845906257629,
                    "y":0.5384615659713745
                },
                {
                    "x":0.6461538672447205,
                    "y":0.5692307949066162
                },
                {
                    "x":0.5884615182876587,
                    "y":0.5846153497695923
                }
            ],
            [
                {
                    "x":0.36153846979141235,
                    "y":0.3115384578704834
                },
                {
                    "x":0.5730769038200378,
                    "y":0.38461536169052124
                },
                {
                    "x":0.5884615182876587,
                    "y":0.39615386724472046
                },
                {
                    "x":0.5846154093742371,
                    "y":0.4038461446762085
                }
            ],
            [
                {
                    "x":0.607692301273346,
                    "y":0.6499999761581421
                },
                {
                    "x":0.6230769157409668,
                    "y":0.6576923131942749
                },
                {
                    "x":0.5961538553237915,
                    "y":0.6615384817123413
                },
                {
                    "x":0.5913609266281128,
                    "y":0.64715975522995
                }
            ],
            [
                {
                    "x":0.5884615182876587,
                    "y":0.6384615302085876
                },
                {
                    "x":0.6230769157409668,
                    "y":0.6461538076400757
                },
                {
                    "x":0.607692301273346,
                    "y":0.6499999761581421
                },
                {
                    "x":0.5913609266281128,
                    "y":0.64715975522995
                }
            ],
            [
                {
                    "x":0.5961538553237915,
                    "y":0.6615384817123413
                },
                {
                    "x":0.3692307770252228,
                    "y":0.75
                },
                {
                    "x":0.3153846263885498,
                    "y":0.7230769395828247
                },
                {
                    "x":0.3192307651042938,
                    "y":0.699999988079071
                },
                {
                    "x":0.36153846979141235,
                    "y":0.6846153736114502
                },
                {
                    "x":0.5769230723381042,
                    "y":0.6192307472229004
                },
                {
                    "x":0.5884615182876587,
                    "y":0.6384615302085876
                }
            ],
            [
                {
                    "x":0.6538461446762085,
                    "y":0.6961538791656494
                },
                {
                    "x":0.6692307591438293,
                    "y":0.7038461565971375
                },
                {
                    "x":0.6538461446762085,
                    "y":0.7076922655105591
                },
                {
                    "x":0.3692307770252228,
                    "y":0.7653846144676208
                },
                {
                    "x":0.3692307770252228,
                    "y":0.75
                }
            ],
            [
                {
                    "x":0.3692307770252228,
                    "y":0.75
                },
                {
                    "x":0.6153846383094788,
                    "y":0.6846153736114502
                },
                {
                    "x":0.6692307591438293,
                    "y":0.692307710647583
                },
                {
                    "x":0.6538461446762085,
                    "y":0.6961538791656494
                }
            ],
            [
                {
                    "x":0.3692307770252228,
                    "y":0.75
                },
                {
                    "x":0.5961538553237915,
                    "y":0.6615384817123413
                },
                {
                    "x":0.6153846383094788,
                    "y":0.6846153736114502
                }
            ],
            [
                {
                    "x":0.7769230604171753,
                    "y":0.7461538314819336
                },
                {
                    "x":0.9884615540504456,
                    "y":0.75
                },
                {
                    "x":0.9692307710647583,
                    "y":0.7692307829856873
                },
                {
                    "x":0.8692307472229004,
                    "y":0.7961538434028625
                },
                {
                    "x":0.7038461565971375,
                    "y":0.8153846263885498
                }
            ],
            [
                {
                    "x":0.7038461565971375,
                    "y":0.8153846263885498
                },
                {
                    "x":0.6807692050933838,
                    "y":0.7307692170143127
                },
                {
                    "x":0.7769230604171753,
                    "y":0.7461538314819336
                }
            ],
            [
                {
                    "x":0.7038461565971375,
                    "y":0.8153846263885498
                },
                {
                    "x":0.48461538553237915,
                    "y":0.8192307949066162
                },
                {
                    "x":0.2730769217014313,
                    "y":0.807692289352417
                },
                {
                    "x":0.2807692289352417,
                    "y":0.7923076748847961
                },
                {
                    "x":0.3692307770252228,
                    "y":0.7653846144676208
                },
                {
                    "x":0.6538461446762085,
                    "y":0.7076922655105591
                },
                {
                    "x":0.6807692050933838,
                    "y":0.7307692170143127
                }
            ]
        ],
        "circles":[

        ],
        "shapes":[
            {
                "type":"POLYGON",
                "vertices":[
                    {
                        "x":0.48461538553237915,
                        "y":0.8192307949066162
                    },
                    {
                        "x":0.7038461565971375,
                        "y":0.8153846263885498
                    },
                    {
                        "x":0.8692307472229004,
                        "y":0.7961538434028625
                    },
                    {
                        "x":0.9692307710647583,
                        "y":0.7692307829856873
                    },
                    {
                        "x":0.9884615540504456,
                        "y":0.75
                    },
                    {
                        "x":0.7769230604171753,
                        "y":0.7461538314819336
                    },
                    {
                        "x":0.6807692050933838,
                        "y":0.7307692170143127
                    },
                    {
                        "x":0.6538461446762085,
                        "y":0.7076922655105591
                    },
                    {
                        "x":0.6692307591438293,
                        "y":0.7038461565971375
                    },
                    {
                        "x":0.6538461446762085,
                        "y":0.6961538791656494
                    },
                    {
                        "x":0.6692307591438293,
                        "y":0.692307710647583
                    },
                    {
                        "x":0.6153846383094788,
                        "y":0.6846153736114502
                    },
                    {
                        "x":0.5961538553237915,
                        "y":0.6615384817123413
                    },
                    {
                        "x":0.6230769157409668,
                        "y":0.6576923131942749
                    },
                    {
                        "x":0.607692301273346,
                        "y":0.6499999761581421
                    },
                    {
                        "x":0.6230769157409668,
                        "y":0.6461538076400757
                    },
                    {
                        "x":0.5884615182876587,
                        "y":0.6384615302085876
                    },
                    {
                        "x":0.5769230723381042,
                        "y":0.6192307472229004
                    },
                    {
                        "x":0.6038461327552795,
                        "y":0.615384578704834
                    },
                    {
                        "x":0.5884615182876587,
                        "y":0.607692301273346
                    },
                    {
                        "x":0.6038461327552795,
                        "y":0.6038461923599243
                    },
                    {
                        "x":0.5846154093742371,
                        "y":0.6000000238418579
                    },
                    {
                        "x":0.5884615182876587,
                        "y":0.5846153497695923
                    },
                    {
                        "x":0.6461538672447205,
                        "y":0.5692307949066162
                    },
                    {
                        "x":0.6653845906257629,
                        "y":0.5384615659713745
                    },
                    {
                        "x":0.7038461565971375,
                        "y":0.5230768918991089
                    },
                    {
                        "x":0.7153846025466919,
                        "y":0.4961538314819336
                    },
                    {
                        "x":0.6692307591438293,
                        "y":0.4692307710647583
                    },
                    {
                        "x":0.6692307591438293,
                        "y":0.44615381956100464
                    },
                    {
                        "x":0.607692301273346,
                        "y":0.4307692050933838
                    },
                    {
                        "x":0.5846154093742371,
                        "y":0.4038461446762085
                    },
                    {
                        "x":0.6038461327552795,
                        "y":0.4038461446762085
                    },
                    {
                        "x":0.5884615182876587,
                        "y":0.39615386724472046
                    },
                    {
                        "x":0.6038461327552795,
                        "y":0.39230769872665405
                    },
                    {
                        "x":0.5730769038200378,
                        "y":0.38461536169052124
                    },
                    {
                        "x":0.5807692408561707,
                        "y":0.36538463830947876
                    },
                    {
                        "x":0.6230769157409668,
                        "y":0.36153846979141235
                    },
                    {
                        "x":0.607692301273346,
                        "y":0.35384613275527954
                    },
                    {
                        "x":0.6230769157409668,
                        "y":0.3500000238418579
                    },
                    {
                        "x":0.5961538553237915,
                        "y":0.3423076868057251
                    },
                    {
                        "x":0.6153846383094788,
                        "y":0.3192307949066162
                    },
                    {
                        "x":0.6692307591438293,
                        "y":0.3153846263885498
                    },
                    {
                        "x":0.6538461446762085,
                        "y":0.307692289352417
                    },
                    {
                        "x":0.6692307591438293,
                        "y":0.30384618043899536
                    },
                    {
                        "x":0.6538461446762085,
                        "y":0.29615384340286255
                    },
                    {
                        "x":0.6807692050933838,
                        "y":0.27307695150375366
                    },
                    {
                        "x":0.75,
                        "y":0.2576923370361328
                    },
                    {
                        "x":0.9961538314819336,
                        "y":0.2538461685180664
                    },
                    {
                        "x":0.9692307710647583,
                        "y":0.23461538553237915
                    },
                    {
                        "x":0.8346154093742371,
                        "y":0.19999998807907104
                    },
                    {
                        "x":0.6384615302085876,
                        "y":0.1846153736114502
                    },
                    {
                        "x":0.29615384340286255,
                        "y":0.192307710647583
                    },
                    {
                        "x":0.26153847575187683,
                        "y":0.20769232511520386
                    },
                    {
                        "x":0.3153846263885498,
                        "y":0.2192307710647583
                    },
                    {
                        "x":0.3692307770252228,
                        "y":0.2538461685180664
                    },
                    {
                        "x":0.32307693362236023,
                        "y":0.26153844594955444
                    },
                    {
                        "x":0.3153846263885498,
                        "y":0.2846153974533081
                    },
                    {
                        "x":0.36153846979141235,
                        "y":0.3115384578704834
                    },
                    {
                        "x":0.3346153795719147,
                        "y":0.3461538553237915
                    },
                    {
                        "x":0.33076924085617065,
                        "y":0.38846153020858765
                    },
                    {
                        "x":0.23846153914928436,
                        "y":0.4115384817123413
                    },
                    {
                        "x":0.17307692766189575,
                        "y":0.4076923131942749
                    },
                    {
                        "x":0.13076923787593842,
                        "y":0.39230769872665405
                    },
                    {
                        "x":0.13076923787593842,
                        "y":0.4115384817123413
                    },
                    {
                        "x":0.003846153849735856,
                        "y":0.36153846979141235
                    },
                    {
                        "x":0.0615384615957737,
                        "y":0.3999999761581421
                    },
                    {
                        "x":0.057692307978868484,
                        "y":0.41538459062576294
                    },
                    {
                        "x":0.03076923079788685,
                        "y":0.41538459062576294
                    },
                    {
                        "x":0.057692307978868484,
                        "y":0.442307710647583
                    },
                    {
                        "x":0.05000000074505806,
                        "y":0.45769232511520386
                    },
                    {
                        "x":0.01923076994717121,
                        "y":0.45769232511520386
                    },
                    {
                        "x":0.01923076994717121,
                        "y":0.5346153974533081
                    },
                    {
                        "x":0.05384615436196327,
                        "y":0.5461538434028625
                    },
                    {
                        "x":0.05384615436196327,
                        "y":0.5653846263885498
                    },
                    {
                        "x":0.023076923564076424,
                        "y":0.5807692408561707
                    },
                    {
                        "x":0.06538461893796921,
                        "y":0.5884615182876587
                    },
                    {
                        "x":0,
                        "y":0.642307698726654
                    },
                    {
                        "x":0.11923076957464218,
                        "y":0.5923076868057251
                    },
                    {
                        "x":0.13076923787593842,
                        "y":0.615384578704834
                    },
                    {
                        "x":0.18076923489570618,
                        "y":0.5923076868057251
                    },
                    {
                        "x":0.3192307651042938,
                        "y":0.6038461923599243
                    },
                    {
                        "x":0.33076924085617065,
                        "y":0.6499999761581421
                    },
                    {
                        "x":0.36153846979141235,
                        "y":0.6846153736114502
                    },
                    {
                        "x":0.3192307651042938,
                        "y":0.699999988079071
                    },
                    {
                        "x":0.3153846263885498,
                        "y":0.7230769395828247
                    },
                    {
                        "x":0.3692307770252228,
                        "y":0.75
                    },
                    {
                        "x":0.3692307770252228,
                        "y":0.7653846144676208
                    },
                    {
                        "x":0.2807692289352417,
                        "y":0.7923076748847961
                    },
                    {
                        "x":0.2730769217014313,
                        "y":0.807692289352417
                    }
                ]
            }
        ]
    },
    "dynamicObjects":[

    ]
}

